crsmysql/__init__.py
crsmysql/crsmysql.py
crsmysql-1.1.0.dist-info/LICENSE
crsmysql-1.1.0.dist-info/METADATA
crsmysql-1.1.0.dist-info/WHEEL
crsmysql-1.1.0.dist-info/top_level.txt
crsmysql-1.1.0.dist-info/RECORD
