Metadata-Version: 2.1
Name: crsmysql
Version: 1.1.0
Summary: This is my personal mysql toolkit.
Home-page: https://github.com/wsywddr
Author: Chris Chen
Author-email: wsywddr@163.com
License: UNKNOWN
Platform: UNKNOWN
Classifier: Programming Language :: Python :: 3
Classifier: License :: OSI Approved :: MIT License
Classifier: Operating System :: OS Independent
Requires-Dist: PyMySQL (==0.9.3)
